ort_gpu_nightly_featurizer-1.3.1.dev202006261.data/purelib/onnxruntime/LICENSE
ort_gpu_nightly_featurizer-1.3.1.dev202006261.data/purelib/onnxruntime/Privacy.md
ort_gpu_nightly_featurizer-1.3.1.dev202006261.data/purelib/onnxruntime/ThirdPartyNotices.txt
ort_gpu_nightly_featurizer-1.3.1.dev202006261.data/purelib/onnxruntime/__init__.py
ort_gpu_nightly_featurizer-1.3.1.dev202006261.data/purelib/onnxruntime/FeaturizersLibrary/Data/DateTimeFeaturizer/Argentina.json
ort_gpu_nightly_featurizer-1.3.1.dev202006261.data/purelib/onnxruntime/FeaturizersLibrary/Data/DateTimeFeaturizer/Australia.json
ort_gpu_nightly_featurizer-1.3.1.dev202006261.data/purelib/onnxruntime/FeaturizersLibrary/Data/DateTimeFeaturizer/Austria.json
ort_gpu_nightly_featurizer-1.3.1.dev202006261.data/purelib/onnxruntime/FeaturizersLibrary/Data/DateTimeFeaturizer/Belarus.json
ort_gpu_nightly_featurizer-1.3.1.dev202006261.data/purelib/onnxruntime/FeaturizersLibrary/Data/DateTimeFeaturizer/Belgium.json
ort_gpu_nightly_featurizer-1.3.1.dev202006261.data/purelib/onnxruntime/FeaturizersLibrary/Data/DateTimeFeaturizer/Brazil.json
ort_gpu_nightly_featurizer-1.3.1.dev202006261.data/purelib/onnxruntime/FeaturizersLibrary/Data/DateTimeFeaturizer/Canada.json
ort_gpu_nightly_featurizer-1.3.1.dev202006261.data/purelib/onnxruntime/FeaturizersLibrary/Data/DateTimeFeaturizer/Colombia.json
ort_gpu_nightly_featurizer-1.3.1.dev202006261.data/purelib/onnxruntime/FeaturizersLibrary/Data/DateTimeFeaturizer/Croatia.json
ort_gpu_nightly_featurizer-1.3.1.dev202006261.data/purelib/onnxruntime/FeaturizersLibrary/Data/DateTimeFeaturizer/Czech.json
ort_gpu_nightly_featurizer-1.3.1.dev202006261.data/purelib/onnxruntime/FeaturizersLibrary/Data/DateTimeFeaturizer/Denmark.json
ort_gpu_nightly_featurizer-1.3.1.dev202006261.data/purelib/onnxruntime/FeaturizersLibrary/Data/DateTimeFeaturizer/England.json
ort_gpu_nightly_featurizer-1.3.1.dev202006261.data/purelib/onnxruntime/FeaturizersLibrary/Data/DateTimeFeaturizer/Finland.json
ort_gpu_nightly_featurizer-1.3.1.dev202006261.dist-info/METADATA
ort_gpu_nightly_featurizer-1.3.1.dev202006261.dist-info/WHEEL
ort_gpu_nightly_featurizer-1.3.1.dev202006261.dist-info/entry_points.txt
ort_gpu_nightly_featurizer-1.3.1.dev202006261.dist-info/top_level.txt
ort_gpu_nightly_featurizer-1.3.1.dev202006261.dist-info/RECORD
